DESCRIPTION
MANIFEST.in
VERSION.txt
setup.cfg
setup.py
pijon/__init__.py
pijon/pijon.py
pijon.egg-info/PKG-INFO
pijon.egg-info/SOURCES.txt
pijon.egg-info/dependency_links.txt
pijon.egg-info/top_level.txt
scripts/pijon