Metadata-Version: 1.1
Name: pijon
Version: 0.1.0
Summary: Tool and library to help with json based schema and data migration.
Home-page: http://www.surycat.com
Author: Optiflows R&D
Author-email: rand@surycat.com
License: Apache 2.0
Platform: UNKNOWN
Classifier: Development Status :: 2 - Pre-Alpha
Classifier: Intended Audience :: Developers
Classifier: Natural Language :: English
Classifier: License :: OSI Approved :: Apache Software License
Classifier: Programming Language :: Python :: 3.5
Classifier: Programming Language :: Python :: 3 :: Only
